{
	"name": "pl_sql_adls",
	"properties": {
		"activities": [
			{
				"name": "get_water_mark_last_updated",
				"type": "Lookup",
				"dependsOn": [],
				"policy": {
					"timeout": "0.12:00:00",
					"retry": 0,
					"retryIntervalInSeconds": 30,
					"secureOutput": false,
					"secureInput": false
				},
				"userProperties": [],
				"typeProperties": {
					"source": {
						"type": "SqlServerSource",
						"sqlReaderQuery": "select Watermarkvalue from watermarktable order by Watermarkvalue DESC",
						"queryTimeout": "02:00:00",
						"partitionOption": "None"
					},
					"dataset": {
						"referenceName": "SqlServerTable1",
						"type": "DatasetReference"
					},
					"firstRowOnly": true
				}
			},
			{
				"name": "get_water_mark_new",
				"type": "Lookup",
				"dependsOn": [],
				"policy": {
					"timeout": "0.12:00:00",
					"retry": 0,
					"retryIntervalInSeconds": 30,
					"secureOutput": false,
					"secureInput": false
				},
				"userProperties": [],
				"typeProperties": {
					"source": {
						"type": "SqlServerSource",
						"sqlReaderQuery": "select max(emp_id) as NewWaterMarkValue from employee",
						"queryTimeout": "02:00:00",
						"partitionOption": "None"
					},
					"dataset": {
						"referenceName": "SqlServerTable1",
						"type": "DatasetReference"
					},
					"firstRowOnly": true
				}
			},
			{
				"name": "Copy data1",
				"type": "Copy",
				"dependsOn": [
					{
						"activity": "get_water_mark_last_updated",
						"dependencyConditions": [
							"Succeeded"
						]
					},
					{
						"activity": "get_water_mark_new",
						"dependencyConditions": [
							"Succeeded"
						]
					}
				],
				"policy": {
					"timeout": "0.12:00:00",
					"retry": 0,
					"retryIntervalInSeconds": 30,
					"secureOutput": false,
					"secureInput": false
				},
				"userProperties": [],
				"typeProperties": {
					"source": {
						"type": "SqlServerSource",
						"sqlReaderQuery": {
							"value": "select * from employee where emp_id > \n'@{activity('get_water_mark_last_updated').output.firstRow.Watermarkvalue}' \nand emp_id < = '@{activity('get_water_mark_new').output.firstRow.NewWaterMarkValue}'",
							"type": "Expression"
						},
						"queryTimeout": "02:00:00",
						"partitionOption": "None"
					},
					"enableStaging": false
				},
				"inputs": [
					{
						"referenceName": "SqlServerTable1",
						"type": "DatasetReference"
					}
				]
			}
		],
		"annotations": []
	}
}